<!DOCTYPE suite SYSTEM "http://testng.org/testng-1.0.dtd" >
<suite name="bvt suit" parallel="tests" thread-count="1">
<!--    <listeners>-->
<!--        <listener class-name="com.cutanddry.qa.utils.RetryTransformer"/>-->
<!--        <listener class-name="com.cutanddry.qa.utils.TestNGListener"/>-->
<!--        <listener class-name="com.cutanddry.qa.utils.AIOSampleUIMethodListener"/>-->
<!--    </listeners>-->
    <test name="synthetic monitoring tests">
        <parameter name="DP" value="KK International, Inc - Operator Name: Be.steak.a Llc (18935) - Campbell , Owner: chefstout99@gmail.com" />
        <classes>
            <class name="com.cutanddry.qa.synthetic_monitoring.kk.owner.VerifyCustomerOrderGuideTest" />
            <class name="com.cutanddry.qa.synthetic_monitoring.kk.owner.VerifyCustomerCatalogTest" />
            <class name="com.cutanddry.qa.synthetic_monitoring.kk.owner.VerifyCustomerEditTest" />
            <class name="com.cutanddry.qa.synthetic_monitoring.kk.owner.VerifyCustomerSearchTest" />
            <class name="com.cutanddry.qa.synthetic_monitoring.kk.owner.VerifyTheDraftsTest" />
            <class name="com.cutanddry.qa.synthetic_monitoring.kk.owner.VerifyTheChatTest" />
            <class name="com.cutanddry.qa.synthetic_monitoring.kk.owner.VerifySettingsProfileTest" />
            <class name="com.cutanddry.qa.synthetic_monitoring.kk.owner.VerifySettingsBusinessTest" />
            <class name="com.cutanddry.qa.synthetic_monitoring.kk.owner.VerifySettingsLocationTest" />
            <class name="com.cutanddry.qa.synthetic_monitoring.kk.owner.VerifySettingsAccountingTest" />
            <class name="com.cutanddry.qa.synthetic_monitoring.kk.owner.VerifyThePaySectionTest" />
            <class name="com.cutanddry.qa.synthetic_monitoring.kk.owner.VerifyTheHistoryTest" />
            <class name="com.cutanddry.qa.synthetic_monitoring.kk.owner.VerifyTheUsersTest" />
            <class name="com.cutanddry.qa.synthetic_monitoring.kk.owner.VerifyTheReportsTest" />
            <class name="com.cutanddry.qa.synthetic_monitoring.kk.owner.VerifyTheSuppliersTest" />
            <class name="com.cutanddry.qa.synthetic_monitoring.kk.owner.VerifyTheSupportTest" />
            <class name="com.cutanddry.qa.synthetic_monitoring.kk.owner.VerifyTheRewardsTest" />
        </classes>
    </test>
</suite>